datacentertracesdatasets_cli/__init__.py
datacentertracesdatasets_cli/cli.py
datacentertracesdatasets_cli-1.0.dist-info/LICENSE
datacentertracesdatasets_cli-1.0.dist-info/METADATA
datacentertracesdatasets_cli-1.0.dist-info/WHEEL
datacentertracesdatasets_cli-1.0.dist-info/entry_points.txt
datacentertracesdatasets_cli-1.0.dist-info/top_level.txt
datacentertracesdatasets_cli-1.0.dist-info/RECORD
