Metadata-Version: 2.1
Name: datacentertracesdatasets-cli
Version: 1.0
Summary: Datacentertracesdatasets-cli is an open-source tool designed to facilitate the usage of Datacentertracesdatasets package from a command line interface
Author-email: Alejandro Fernández-Montes <afdez@us.es>, Damián Fernández-Cerero <damiancerero@us.es>
Project-URL: Homepage, https://github.com/alejandrofdez-us/similarity-ts-cli
Project-URL: Bug Tracker, https://github.com/alejandrofdez-us/similarity-ts-cli/issues
Classifier: Programming Language :: Python :: 3
Classifier: License :: OSI Approved :: MIT License
Classifier: Operating System :: OS Independent
Requires-Python: >=3.9
License-File: LICENSE
Requires-Dist: datacentertracesdatasets
Requires-Dist: pandas
